setup.py
documd/__init__.py
documd/documentation.py
documd/models.py
documd.egg-info/PKG-INFO
documd.egg-info/SOURCES.txt
documd.egg-info/dependency_links.txt
documd.egg-info/top_level.txt
test/tests.py