Metadata-Version: 1.0
Name: documd
Version: 0.1.1
Summary: Simple markdown documentation from docstrings
Home-page: https://github.com/projectweekend/documd
Author: Brian Hines
Author-email: brian@projectweekend.net
License: MIT
Platform: UNKNOWN
